mboauth2/__init__.py
mboauth2/app.py
mboauth2/py.typed
mboauth2-0.1.4.dist-info/METADATA
mboauth2-0.1.4.dist-info/WHEEL
mboauth2-0.1.4.dist-info/RECORD
