Metadata-Version: 2.1
Name: mboauth2
Version: 0.1.4
Summary: 
Author: Dr-Blank
Author-email: 64108942+Dr-Blank@users.noreply.github.com
Requires-Python: >=3.10,<4.0
Classifier: Programming Language :: Python :: 3
Classifier: Programming Language :: Python :: 3.10
Classifier: Programming Language :: Python :: 3.11
Classifier: Programming Language :: Python :: 3.12
Requires-Dist: requests (>=2.31.0,<3.0.0)
